{
    "parent": "aa:quest/magic/sniffer",
    "display": {
        "description": {
            "translate": "advancements.aa.quest.magic.norma_fate.description"
        },
        "frame": "goal",
        "icon": {
            "id": "minecraft:mycelium"
        },
        "title": {
            "translate": "advancements.aa.quest.magic.norma_fate.title"
        }
    },
    "criteria": {
        "norma_fate": {
            "trigger": "minecraft:inventory_changed",
            "conditions": {
                "items": [
                    {
                        "items": "minecraft:written_book",
                        "predicates": {
                            "minecraft:custom_data": {
                                "aa": {
                                    "type": "journal",
                                    "id": "norma.5"
                                }
                            }
                        }
                    }
                ]
            }
        }
    },
    "requirements": [
        [
            "norma_fate"
        ]
    ]
}